{
  "resultCode": "success",
  "resultMsg": "성공",
  "list": [
    {
      "FOND_SC_CODE": "사립",
      "SCHUL_KND_SC_CODE": "02",
      "ADRCD_NM": "서울특별시 강서구",
      "JU_ORG_NM": "서울특별시강서양천교육지원청",
      "ATPT_OFCDC_ORG_NM": "서울특별시교육청",
      "JU_ORG_CODE": "B100000271",
      "AMT8": 0,
      "PBAN_EXCP_YN": "N",
      "AMT7": 116295700,
      "FAS_DTN_SC_CODE": "복식부기",
      "PBAN_REV_EX_SC_CODE": "결산세출",
      "AMT6": 410808890,
      "AMT5": 152492959,
      "AMT4": 1227829880,
      "AMT3": 459257731,
      "AMT2": 809535617,
      "SCHUL_CODE": "S010001061",
      "AMT1": 1642706800,
      "YESAN_PER_HEAD": 14173316.4,
      "ATPT_OFCDC_ORG_CODE": "B100000001",
      "LCTN_SC_CODE": "01",
      "BNHH_YN": "N",
      "SCHUL_NM": "유석초등학교"
    },
    {
      "FOND_SC_CODE": "사립",
      "SCHUL_KND_SC_CODE": "02",
      "ADRCD_NM": "서울특별시 금천구",
      "JU_ORG_NM": "서울특별시남부교육지원청",
      "ATPT_OFCDC_ORG_NM": "서울특별시교육청",
      "JU_ORG_CODE": "B100000282",
      "AMT8": 0,
      "PBAN_EXCP_YN": "N",
      "AMT7": 647526650,
      "FAS_DTN_SC_CODE": "미지정",
      "PBAN_REV_EX_SC_CODE": "결산세출",
      "AMT6": 274400349,
      "AMT5": 681566220,
      "AMT4": 1700319960,
      "AMT3": 877086651,
      "AMT2": 1466467710,
      "SCHUL_CODE": "S010001197",
      "AMT1": 1838607330,
      "YESAN_PER_HEAD": 15961566.9,
      "ATPT_OFCDC_ORG_CODE": "B100000001",
      "LCTN_SC_CODE": "01",
      "BNHH_YN": "N",
      "SCHUL_NM": "동광초등학교"
    },
    {
      "SCHUL_CRSE_SC_VALUE_NM": "초",
      "FOND_SC_CODE": "사립",
      "SCHUL_KND_SC_CODE": "02",
      "ADRCD_NM": "서울특별시 동대문구",
      "SCHUL_CRSE_SC_VALUE": "2",
      "JU_ORG_NM": "서울특별시동부교육지원청",
      "ATPT_OFCDC_ORG_NM": "서울특별시교육청",
      "JU_ORG_CODE": "B100000293",
      "AMT8": 140000000,
      "PBAN_EXCP_YN": "N",
      "AMT7": 456573780,
      "FAS_DTN_SC_CODE": "미지정",
      "PBAN_REV_EX_SC_CODE": "결산세출",
      "AMT6": 290584882,
      "AMT5": 120009160,
      "AMT4": 1378519983,
      "AMT3": 1090452152,
      "AMT2": 1713614200,
      "SCHUL_CODE": "S010001394",
      "AMT1": 3524409230,
      "YESAN_PER_HEAD": 12986830.7,
      "ATPT_OFCDC_ORG_CODE": "B100000001",
      "LCTN_SC_CODE": "01",
      "BNHH_YN": "N",
      "SCHUL_NM": "경희초등학교"
    },
    {
      "SCHUL_CRSE_SC_VALUE_NM": "초",
      "FOND_SC_CODE": "사립",
      "SCHUL_KND_SC_CODE": "02",
      "ADRCD_NM": "서울특별시 중랑구",
      "SCHUL_CRSE_SC_VALUE": "2",
      "JU_ORG_NM": "서울특별시동부교육지원청",
      "ATPT_OFCDC_ORG_NM": "서울특별시교육청",
      "JU_ORG_CODE": "B100000293",
      "AMT8": 0,
      "PBAN_EXCP_YN": "N",
      "AMT7": 615388390,
      "FAS_DTN_SC_CODE": "복식부기",
      "PBAN_REV_EX_SC_CODE": "결산세출",
      "AMT6": 848111374,
      "AMT5": 161486140,
      "AMT4": 572141920,
      "AMT3": 1171929910,
      "AMT2": 1578627660,
      "SCHUL_CODE": "S010001395",
      "AMT1": 3170147010,
      "YESAN_PER_HEAD": 12412587.8,
      "ATPT_OFCDC_ORG_CODE": "B100000001",
      "LCTN_SC_CODE": "01",
      "BNHH_YN": "N",
      "SCHUL_NM": "금성초등학교"
    },
    {
      "FOND_SC_CODE": "사립",
      "SCHUL_KND_SC_CODE": "02",
      "ADRCD_NM": "서울특별시 동대문구",
      "JU_ORG_NM": "서울특별시동부교육지원청",
      "ATPT_OFCDC_ORG_NM": "서울특별시교육청",
      "JU_ORG_CODE": "B100000293",
      "AMT8": 176986,
      "PBAN_EXCP_YN": "N",
      "AMT7": 192270100,
      "FAS_DTN_SC_CODE": "복식부기",
      "PBAN_REV_EX_SC_CODE": "결산세출",
      "AMT6": 384882008,
      "AMT5": 339421295,
      "AMT4": 1755720379,
      "AMT3": 924392374,
      "AMT2": 1704437765,
      "SCHUL_CODE": "S010001396",
      "AMT1": 2517209660,
      "YESAN_PER_HEAD": 10996498.7,
      "ATPT_OFCDC_ORG_CODE": "B100000001",
      "LCTN_SC_CODE": "01",
      "BNHH_YN": "N",
      "SCHUL_NM": "서울삼육초등학교"
    },
    {
      "FOND_SC_CODE": "사립",
      "SCHUL_KND_SC_CODE": "02",
      "ADRCD_NM": "서울특별시 동대문구",
      "JU_ORG_NM": "서울특별시동부교육지원청",
      "ATPT_OFCDC_ORG_NM": "서울특별시교육청",
      "JU_ORG_CODE": "B100000293",
      "AMT8": 0,
      "PBAN_EXCP_YN": "N",
      "AMT7": 578458950,
      "FAS_DTN_SC_CODE": "복식부기",
      "PBAN_REV_EX_SC_CODE": "결산세출",
      "AMT6": 728736965,
      "AMT5": 363348430,
      "AMT4": 1364639070,
      "AMT3": 632031085,
      "AMT2": 1380179710,
      "SCHUL_CODE": "S010001434",
      "AMT1": 4028455224,
      "YESAN_PER_HEAD": 13096463.8,
      "ATPT_OFCDC_ORG_CODE": "B100000001",
      "LCTN_SC_CODE": "01",
      "BNHH_YN": "N",
      "SCHUL_NM": "은석초등학교"
    },
    {
      "FOND_SC_CODE": "사립",
      "SCHUL_KND_SC_CODE": "02",
      "ADRCD_NM": "서울특별시 동작구",
      "JU_ORG_NM": "서울특별시동작관악교육지원청",
      "ATPT_OFCDC_ORG_NM": "서울특별시교육청",
      "JU_ORG_CODE": "B100000304",
      "AMT8": 0,
      "PBAN_EXCP_YN": "N",
      "AMT7": 641891630,
      "FAS_DTN_SC_CODE": "미지정",
      "PBAN_REV_EX_SC_CODE": "결산세출",
      "AMT6": 501227869,
      "AMT5": 497972854,
      "AMT4": 938240613,
      "AMT3": 894398842,
      "AMT2": 1563089786,
      "SCHUL_CODE": "S010001613",
      "AMT1": 4168321130,
      "YESAN_PER_HEAD": 12644426.8,
      "ATPT_OFCDC_ORG_CODE": "B100000001",
      "LCTN_SC_CODE": "01",
      "BNHH_YN": "N",
      "SCHUL_NM": "중앙대학교사범대학부속초등학교"
    },
    {
      "FOND_SC_CODE": "사립",
      "SCHUL_KND_SC_CODE": "02",
      "ADRCD_NM": "서울특별시 도봉구",
      "JU_ORG_NM": "서울특별시북부교육지원청",
      "ATPT_OFCDC_ORG_NM": "서울특별시교육청",
      "JU_ORG_CODE": "B100000315",
      "AMT8": 0,
      "PBAN_EXCP_YN": "N",
      "AMT7": 529799890,
      "FAS_DTN_SC_CODE": "미지정",
      "PBAN_REV_EX_SC_CODE": "결산세출",
      "AMT6": 861326617,
      "AMT5": 330067273,
      "AMT4": 1283177094,
      "AMT3": 1703224240,
      "AMT2": 1816443300,
      "SCHUL_CODE": "S010001733",
      "AMT1": 2523323857,
      "YESAN_PER_HEAD": 12144110.4,
      "ATPT_OFCDC_ORG_CODE": "B100000001",
      "LCTN_SC_CODE": "01",
      "BNHH_YN": "N",
      "SCHUL_NM": "동북초등학교"
    },
    {
      "SCHUL_CRSE_SC_VALUE_NM": "초",
      "FOND_SC_CODE": "사립",
      "SCHUL_KND_SC_CODE": "02",
      "ADRCD_NM": "서울특별시 노원구",
      "SCHUL_CRSE_SC_VALUE": "2",
      "JU_ORG_NM": "서울특별시북부교육지원청",
      "ATPT_OFCDC_ORG_NM": "서울특별시교육청",
      "JU_ORG_CODE": "B100000315",
      "AMT8": 0,
      "PBAN_EXCP_YN": "N",
      "AMT7": 452451760,
      "FAS_DTN_SC_CODE": "복식부기",
      "PBAN_REV_EX_SC_CODE": "결산세출",
      "AMT6": 525991933,
      "AMT5": 174253522,
      "AMT4": 1764478030,
      "AMT3": 891455450,
      "AMT2": 1437258077,
      "SCHUL_CODE": "S010001734",
      "AMT1": 3286006630,
      "YESAN_PER_HEAD": 11866335.7,
      "ATPT_OFCDC_ORG_CODE": "B100000001",
      "LCTN_SC_CODE": "01",
      "BNHH_YN": "N",
      "SCHUL_NM": "상명초등학교"
    },
    {
      "FOND_SC_CODE": "사립",
      "SCHUL_KND_SC_CODE": "02",
      "ADRCD_NM": "서울특별시 노원구",
      "JU_ORG_NM": "서울특별시북부교육지원청",
      "ATPT_OFCDC_ORG_NM": "서울특별시교육청",
      "JU_ORG_CODE": "B100000315",
      "AMT8": 0,
      "PBAN_EXCP_YN": "N",
      "AMT7": 1485771124,
      "FAS_DTN_SC_CODE": "미지정",
      "PBAN_REV_EX_SC_CODE": "결산세출",
      "AMT6": 638936670,
      "AMT5": 501840986,
      "AMT4": 1366308256,
      "AMT3": 1431460736,
      "AMT2": 1289719632,
      "SCHUL_CODE": "S010001792",
      "AMT1": 2915491510,
      "YESAN_PER_HEAD": 13581846.1,
      "ATPT_OFCDC_ORG_CODE": "B100000001",
      "LCTN_SC_CODE": "01",
      "BNHH_YN": "N",
      "SCHUL_NM": "청원초등학교"
    },
    {
      "FOND_SC_CODE": "사립",
      "SCHUL_KND_SC_CODE": "02",
      "ADRCD_NM": "서울특별시 노원구",
      "JU_ORG_NM": "서울특별시북부교육지원청",
      "ATPT_OFCDC_ORG_NM": "서울특별시교육청",
      "JU_ORG_CODE": "B100000315",
      "AMT8": 0,
      "PBAN_EXCP_YN": "N",
      "AMT7": 82268960,
      "FAS_DTN_SC_CODE": "미지정",
      "PBAN_REV_EX_SC_CODE": "결산세출",
      "AMT6": 499767645,
      "AMT5": 275195363,
      "AMT4": 957710330,
      "AMT3": 1520719443,
      "AMT2": 1555516188,
      "SCHUL_CODE": "S010001793",
      "AMT1": 2542514830,
      "YESAN_PER_HEAD": 9806982.5,
      "ATPT_OFCDC_ORG_CODE": "B100000001",
      "LCTN_SC_CODE": "01",
      "BNHH_YN": "N",
      "SCHUL_NM": "태강삼육초등학교"
    },
    {
      "SCHUL_CRSE_SC_VALUE_NM": "초",
      "FOND_SC_CODE": "사립",
      "SCHUL_KND_SC_CODE": "02",
      "ADRCD_NM": "서울특별시 도봉구",
      "SCHUL_CRSE_SC_VALUE": "2",
      "JU_ORG_NM": "서울특별시북부교육지원청",
      "ATPT_OFCDC_ORG_NM": "서울특별시교육청",
      "JU_ORG_CODE": "B100000315",
      "AMT8": 11571250,
      "PBAN_EXCP_YN": "N",
      "AMT7": 367878330,
      "FAS_DTN_SC_CODE": "미지정",
      "PBAN_REV_EX_SC_CODE": "결산세출",
      "AMT6": 456328766,
      "AMT5": 460266011,
      "AMT4": 1911010775,
      "AMT3": 970146615,
      "AMT2": 1858556556,
      "SCHUL_CODE": "S010001794",
      "AMT1": 2425614550,
      "YESAN_PER_HEAD": 14715431,
      "ATPT_OFCDC_ORG_CODE": "B100000001",
      "LCTN_SC_CODE": "01",
      "BNHH_YN": "N",
      "SCHUL_NM": "한신초등학교"
    },
    {
      "FOND_SC_CODE": "사립",
      "SCHUL_KND_SC_CODE": "02",
      "ADRCD_NM": "서울특별시 노원구",
      "JU_ORG_NM": "서울특별시북부교육지원청",
      "ATPT_OFCDC_ORG_NM": "서울특별시교육청",
      "JU_ORG_CODE": "B100000315",
      "AMT8": 0,
      "PBAN_EXCP_YN": "N",
      "AMT7": 78368000,
      "FAS_DTN_SC_CODE": "미지정",
      "PBAN_REV_EX_SC_CODE": "결산세출",
      "AMT6": 906885971,
      "AMT5": 433479858,
      "AMT4": 1626616902,
      "AMT3": 1011463903,
      "AMT2": 1701389150,
      "SCHUL_CODE": "S010001795",
      "AMT1": 3264463351,
      "YESAN_PER_HEAD": 13796127.1,
      "ATPT_OFCDC_ORG_CODE": "B100000001",
      "LCTN_SC_CODE": "01",
      "BNHH_YN": "N",
      "SCHUL_NM": "화랑초등학교"
    },
    {
      "FOND_SC_CODE": "사립",
      "SCHUL_KND_SC_CODE": "02",
      "ADRCD_NM": "서울특별시 서대문구",
      "JU_ORG_NM": "서울특별시서부교육지원청",
      "ATPT_OFCDC_ORG_NM": "서울특별시교육청",
      "JU_ORG_CODE": "B100000326",
      "AMT8": 0,
      "PBAN_EXCP_YN": "N",
      "AMT7": 233852000,
      "FAS_DTN_SC_CODE": "미지정",
      "PBAN_REV_EX_SC_CODE": "결산세출",
      "AMT6": 819453686,
      "AMT5": 153726870,
      "AMT4": 616046980,
      "AMT3": 981873631,
      "AMT2": 1528330737,
      "SCHUL_CODE": "S010001966",
      "AMT1": 3942522310,
      "YESAN_PER_HEAD": 14417780.9,
      "ATPT_OFCDC_ORG_CODE": "B100000001",
      "LCTN_SC_CODE": "01",
      "BNHH_YN": "N",
      "SCHUL_NM": "경기초등학교"
    },
    {
      "FOND_SC_CODE": "사립",
      "SCHUL_KND_SC_CODE": "02",
      "ADRCD_NM": "서울특별시 서대문구",
      "JU_ORG_NM": "서울특별시서부교육지원청",
      "ATPT_OFCDC_ORG_NM": "서울특별시교육청",
      "JU_ORG_CODE": "B100000326",
      "AMT8": 0,
      "PBAN_EXCP_YN": "N",
      "AMT7": 434886900,
      "FAS_DTN_SC_CODE": "미지정",
      "PBAN_REV_EX_SC_CODE": "결산세출",
      "AMT6": 452378509,
      "AMT5": 360392010,
      "AMT4": 1427010710,
      "AMT3": 443066846,
      "AMT2": 923432350,
      "SCHUL_CODE": "S010001967",
      "AMT1": 4284163327,
      "YESAN_PER_HEAD": 11808979.6,
      "ATPT_OFCDC_ORG_CODE": "B100000001",
      "LCTN_SC_CODE": "01",
      "BNHH_YN": "N",
      "SCHUL_NM": "명지초등학교"
    },
    {
      "SCHUL_CRSE_SC_VALUE_NM": "초",
      "FOND_SC_CODE": "사립",
      "SCHUL_KND_SC_CODE": "02",
      "ADRCD_NM": "서울특별시 은평구",
      "SCHUL_CRSE_SC_VALUE": "2",
      "JU_ORG_NM": "서울특별시서부교육지원청",
      "ATPT_OFCDC_ORG_NM": "서울특별시교육청",
      "JU_ORG_CODE": "B100000326",
      "AMT8": 0,
      "PBAN_EXCP_YN": "N",
      "AMT7": 178111200,
      "FAS_DTN_SC_CODE": "복식부기",
      "PBAN_REV_EX_SC_CODE": "결산세출",
      "AMT6": 331356982,
      "AMT5": 201198083,
      "AMT4": 832140760,
      "AMT3": 427226022,
      "AMT2": 1127420420,
      "SCHUL_CODE": "S010002019",
      "AMT1": 2849726220,
      "YESAN_PER_HEAD": 13455157.7,
      "ATPT_OFCDC_ORG_CODE": "B100000001",
      "LCTN_SC_CODE": "01",
      "BNHH_YN": "N",
      "SCHUL_NM": "선일초등학교"
    },
    {
      "FOND_SC_CODE": "사립",
      "SCHUL_KND_SC_CODE": "02",
      "ADRCD_NM": "서울특별시 은평구",
      "JU_ORG_NM": "서울특별시서부교육지원청",
      "ATPT_OFCDC_ORG_NM": "서울특별시교육청",
      "JU_ORG_CODE": "B100000326",
      "AMT8": 0,
      "PBAN_EXCP_YN": "N",
      "AMT7": 74814000,
      "FAS_DTN_SC_CODE": "미지정",
      "PBAN_REV_EX_SC_CODE": "결산세출",
      "AMT6": 528858349,
      "AMT5": 151011760,
      "AMT4": 719311270,
      "AMT3": 873626474,
      "AMT2": 1356378440,
      "SCHUL_CODE": "S010002021",
      "AMT1": 1803829090,
      "YESAN_PER_HEAD": 11498600,
      "ATPT_OFCDC_ORG_CODE": "B100000001",
      "LCTN_SC_CODE": "01",
      "BNHH_YN": "N",
      "SCHUL_NM": "예일초등학교"
    },
    {
      "FOND_SC_CODE": "사립",
      "SCHUL_KND_SC_CODE": "02",
      "ADRCD_NM": "서울특별시 서대문구",
      "JU_ORG_NM": "서울특별시서부교육지원청",
      "ATPT_OFCDC_ORG_NM": "서울특별시교육청",
      "JU_ORG_CODE": "B100000326",
      "AMT8": 4209400,
      "PBAN_EXCP_YN": "N",
      "AMT7": 43828161,
      "FAS_DTN_SC_CODE": "미지정",
      "PBAN_REV_EX_SC_CODE": "결산세출",
      "AMT6": 551080905,
      "AMT5": 215356746,
      "AMT4": 1102995200,
      "AMT3": 316049463,
      "AMT2": 807638545,
      "SCHUL_CODE": "S010002023",
      "AMT1": 4784061595,
      "YESAN_PER_HEAD": 12540416.7,
      "ATPT_OFCDC_ORG_CODE": "B100000001",
      "LCTN_SC_CODE": "01",
      "BNHH_YN": "N",
      "SCHUL_NM": "이화여자대학교사범대학부속초등학교"
    },
    {
      "FOND_SC_CODE": "사립",
      "SCHUL_KND_SC_CODE": "02",
      "ADRCD_NM": "서울특별시 서대문구",
      "JU_ORG_NM": "서울특별시서부교육지원청",
      "ATPT_OFCDC_ORG_NM": "서울특별시교육청",
      "JU_ORG_CODE": "B100000326",
      "AMT8": 0,
      "PBAN_EXCP_YN": "N",
      "AMT7": 336521120,
      "FAS_DTN_SC_CODE": "미지정",
      "PBAN_REV_EX_SC_CODE": "결산세출",
      "AMT6": 322763900,
      "AMT5": 178802363,
      "AMT4": 507645990,
      "AMT3": 480652170,
      "AMT2": 867271550,
      "SCHUL_CODE": "S010002024",
      "AMT1": 1791990360,
      "YESAN_PER_HEAD": 12564838.8,
      "ATPT_OFCDC_ORG_CODE": "B100000001",
      "LCTN_SC_CODE": "01",
      "BNHH_YN": "N",
      "SCHUL_NM": "추계초등학교"
    },
    {
      "FOND_SC_CODE": "사립",
      "SCHUL_KND_SC_CODE": "02",
      "ADRCD_NM": "서울특별시 은평구",
      "JU_ORG_NM": "서울특별시서부교육지원청",
      "ATPT_OFCDC_ORG_NM": "서울특별시교육청",
      "JU_ORG_CODE": "B100000326",
      "AMT8": 478864000,
      "PBAN_EXCP_YN": "N",
      "AMT7": 576013000,
      "FAS_DTN_SC_CODE": "복식부기",
      "PBAN_REV_EX_SC_CODE": "결산세출",
      "AMT6": 492777788,
      "AMT5": 562302934,
      "AMT4": 736969720,
      "AMT3": 973565665,
      "AMT2": 1859182355,
      "SCHUL_CODE": "S010002025",
      "AMT1": 3468384160,
      "YESAN_PER_HEAD": 13715231.8,
      "ATPT_OFCDC_ORG_CODE": "B100000001",
      "LCTN_SC_CODE": "01",
      "BNHH_YN": "N",
      "SCHUL_NM": "충암초등학교"
    },
    {
      "FOND_SC_CODE": "사립",
      "SCHUL_KND_SC_CODE": "02",
      "ADRCD_NM": "서울특별시 마포구",
      "JU_ORG_NM": "서울특별시서부교육지원청",
      "ATPT_OFCDC_ORG_NM": "서울특별시교육청",
      "JU_ORG_CODE": "B100000326",
      "AMT8": 0,
      "PBAN_EXCP_YN": "N",
      "AMT7": 0,
      "FAS_DTN_SC_CODE": "복식부기",
      "PBAN_REV_EX_SC_CODE": "결산세출",
      "AMT6": 658685518,
      "AMT5": 231694466,
      "AMT4": 568099993,
      "AMT3": 1235330795,
      "AMT2": 1404239063,
      "SCHUL_CODE": "S010002026",
      "AMT1": 2379759977,
      "YESAN_PER_HEAD": 12776745.2,
      "ATPT_OFCDC_ORG_CODE": "B100000001",
      "LCTN_SC_CODE": "01",
      "BNHH_YN": "N",
      "SCHUL_NM": "홍익대학교사범대학부속초등학교"
    },
    {
      "FOND_SC_CODE": "사립",
      "SCHUL_KND_SC_CODE": "02",
      "ADRCD_NM": "서울특별시 광진구",
      "JU_ORG_NM": "서울특별시성동광진교육지원청",
      "ATPT_OFCDC_ORG_NM": "서울특별시교육청",
      "JU_ORG_CODE": "B100000337",
      "AMT8": 0,
      "PBAN_EXCP_YN": "N",
      "AMT7": 366940830,
      "FAS_DTN_SC_CODE": "미지정",
      "PBAN_REV_EX_SC_CODE": "결산세출",
      "AMT6": 1046010961,
      "AMT5": 329302113,
      "AMT4": 3649575296,
      "AMT3": 1493623923,
      "AMT2": 1054517434,
      "SCHUL_CODE": "S010002163",
      "AMT1": 4940045427,
      "YESAN_PER_HEAD": 17196283,
      "ATPT_OFCDC_ORG_CODE": "B100000001",
      "LCTN_SC_CODE": "01",
      "BNHH_YN": "N",
      "SCHUL_NM": "경복초등학교"
    },
    {
      "FOND_SC_CODE": "사립",
      "SCHUL_KND_SC_CODE": "02",
      "ADRCD_NM": "서울특별시 광진구",
      "JU_ORG_NM": "서울특별시성동광진교육지원청",
      "ATPT_OFCDC_ORG_NM": "서울특별시교육청",
      "JU_ORG_CODE": "B100000337",
      "AMT8": 0,
      "PBAN_EXCP_YN": "N",
      "AMT7": 346394000,
      "FAS_DTN_SC_CODE": "복식부기",
      "PBAN_REV_EX_SC_CODE": "결산세출",
      "AMT6": 352300379,
      "AMT5": 569931372,
      "AMT4": 602495660,
      "AMT3": 1549108870,
      "AMT2": 1751073880,
      "SCHUL_CODE": "S010002196",
      "AMT1": 3711910139,
      "YESAN_PER_HEAD": 12529216.2,
      "ATPT_OFCDC_ORG_CODE": "B100000001",
      "LCTN_SC_CODE": "01",
      "BNHH_YN": "N",
      "SCHUL_NM": "성동초등학교"
    },
    {
      "SCHUL_CRSE_SC_VALUE_NM": "초",
      "FOND_SC_CODE": "사립",
      "SCHUL_KND_SC_CODE": "02",
      "ADRCD_NM": "서울특별시 광진구",
      "SCHUL_CRSE_SC_VALUE": "2",
      "JU_ORG_NM": "서울특별시성동광진교육지원청",
      "ATPT_OFCDC_ORG_NM": "서울특별시교육청",
      "JU_ORG_CODE": "B100000337",
      "AMT8": 15997970,
      "PBAN_EXCP_YN": "N",
      "AMT7": 83495140,
      "FAS_DTN_SC_CODE": "미지정",
      "PBAN_REV_EX_SC_CODE": "결산세출",
      "AMT6": 386002536,
      "AMT5": 187378412,
      "AMT4": 796928936,
      "AMT3": 717197449,
      "AMT2": 1223730235,
      "SCHUL_CODE": "S010002197",
      "AMT1": 2019284650,
      "YESAN_PER_HEAD": 15125390.9,
      "ATPT_OFCDC_ORG_CODE": "B100000001",
      "LCTN_SC_CODE": "01",
      "BNHH_YN": "N",
      "SCHUL_NM": "세종초등학교"
    },
    {
      "FOND_SC_CODE": "사립",
      "SCHUL_KND_SC_CODE": "02",
      "ADRCD_NM": "서울특별시 성동구",
      "JU_ORG_NM": "서울특별시성동광진교육지원청",
      "ATPT_OFCDC_ORG_NM": "서울특별시교육청",
      "JU_ORG_CODE": "B100000337",
      "AMT8": 0,
      "PBAN_EXCP_YN": "N",
      "AMT7": 1604180360,
      "FAS_DTN_SC_CODE": "복식부기",
      "PBAN_REV_EX_SC_CODE": "결산세출",
      "AMT6": 485760541,
      "AMT5": 190527455,
      "AMT4": 1701726190,
      "AMT3": 728421313,
      "AMT2": 887808516,
      "SCHUL_CODE": "S010002198",
      "AMT1": 4635387636,
      "YESAN_PER_HEAD": 15343046.5,
      "ATPT_OFCDC_ORG_CODE": "B100000001",
      "LCTN_SC_CODE": "01",
      "BNHH_YN": "N",
      "SCHUL_NM": "한양초등학교"
    },
    {
      "FOND_SC_CODE": "사립",
      "SCHUL_KND_SC_CODE": "02",
      "ADRCD_NM": "서울특별시 성북구",
      "JU_ORG_NM": "서울특별시성북강북교육지원청",
      "ATPT_OFCDC_ORG_NM": "서울특별시교육청",
      "JU_ORG_CODE": "B100000348",
      "AMT8": 0,
      "PBAN_EXCP_YN": "N",
      "AMT7": 40000000,
      "FAS_DTN_SC_CODE": "복식부기",
      "PBAN_REV_EX_SC_CODE": "결산세출",
      "AMT6": 561001495,
      "AMT5": 346848311,
      "AMT4": 1029898252,
      "AMT3": 816952540,
      "AMT2": 1153488148,
      "SCHUL_CODE": "S010002289",
      "AMT1": 2915154780,
      "YESAN_PER_HEAD": 11692237.7,
      "ATPT_OFCDC_ORG_CODE": "B100000001",
      "LCTN_SC_CODE": "01",
      "BNHH_YN": "N",
      "SCHUL_NM": "광운초등학교"
    },
    {
      "FOND_SC_CODE": "사립",
      "SCHUL_KND_SC_CODE": "02",
      "ADRCD_NM": "서울특별시 성북구",
      "JU_ORG_NM": "서울특별시성북강북교육지원청",
      "ATPT_OFCDC_ORG_NM": "서울특별시교육청",
      "JU_ORG_CODE": "B100000348",
      "AMT8": 0,
      "PBAN_EXCP_YN": "N",
      "AMT7": 321308720,
      "FAS_DTN_SC_CODE": "복식부기",
      "PBAN_REV_EX_SC_CODE": "결산세출",
      "AMT6": 184050367,
      "AMT5": 209675663,
      "AMT4": 1163953349,
      "AMT3": 747942818,
      "AMT2": 1210820439,
      "SCHUL_CODE": "S010002290",
      "AMT1": 2745763570,
      "YESAN_PER_HEAD": 13326953.3,
      "ATPT_OFCDC_ORG_CODE": "B100000001",
      "LCTN_SC_CODE": "01",
      "BNHH_YN": "N",
      "SCHUL_NM": "대광초등학교"
    },
    {
      "FOND_SC_CODE": "사립",
      "SCHUL_KND_SC_CODE": "02",
      "ADRCD_NM": "서울특별시 성북구",
      "JU_ORG_NM": "서울특별시성북강북교육지원청",
      "ATPT_OFCDC_ORG_NM": "서울특별시교육청",
      "JU_ORG_CODE": "B100000348",
      "AMT8": 3136340,
      "PBAN_EXCP_YN": "N",
      "AMT7": 281066282,
      "FAS_DTN_SC_CODE": "미지정",
      "PBAN_REV_EX_SC_CODE": "결산세출",
      "AMT6": 492944056,
      "AMT5": 278839540,
      "AMT4": 1228179930,
      "AMT3": 871193989,
      "AMT2": 1220559650,
      "SCHUL_CODE": "S010002291",
      "AMT1": 2368413970,
      "YESAN_PER_HEAD": 13515698.9,
      "ATPT_OFCDC_ORG_CODE": "B100000001",
      "LCTN_SC_CODE": "01",
      "BNHH_YN": "N",
      "SCHUL_NM": "매원초등학교"
    },
    {
      "FOND_SC_CODE": "사립",
      "SCHUL_KND_SC_CODE": "02",
      "ADRCD_NM": "서울특별시 성북구",
      "JU_ORG_NM": "서울특별시성북강북교육지원청",
      "ATPT_OFCDC_ORG_NM": "서울특별시교육청",
      "JU_ORG_CODE": "B100000348",
      "AMT8": 0,
      "PBAN_EXCP_YN": "N",
      "AMT7": 89618000,
      "FAS_DTN_SC_CODE": "미지정",
      "PBAN_REV_EX_SC_CODE": "결산세출",
      "AMT6": 251228138,
      "AMT5": 393177368,
      "AMT4": 672658940,
      "AMT3": 777516571,
      "AMT2": 1223730290,
      "SCHUL_CODE": "S010002326",
      "AMT1": 2262903540,
      "YESAN_PER_HEAD": 11620559.1,
      "ATPT_OFCDC_ORG_CODE": "B100000001",
      "LCTN_SC_CODE": "01",
      "BNHH_YN": "N",
      "SCHUL_NM": "성신초등학교"
    },
    {
      "FOND_SC_CODE": "사립",
      "SCHUL_KND_SC_CODE": "02",
      "ADRCD_NM": "서울특별시 강북구",
      "JU_ORG_NM": "서울특별시성북강북교육지원청",
      "ATPT_OFCDC_ORG_NM": "서울특별시교육청",
      "JU_ORG_CODE": "B100000348",
      "AMT8": 0,
      "PBAN_EXCP_YN": "N",
      "AMT7": 760052950,
      "FAS_DTN_SC_CODE": "복식부기",
      "PBAN_REV_EX_SC_CODE": "결산세출",
      "AMT6": 985892737,
      "AMT5": 281226610,
      "AMT4": 1911065120,
      "AMT3": 909965605,
      "AMT2": 1494767283,
      "SCHUL_CODE": "S010002327",
      "AMT1": 4635663714,
      "YESAN_PER_HEAD": 16240582.9,
      "ATPT_OFCDC_ORG_CODE": "B100000001",
      "LCTN_SC_CODE": "01",
      "BNHH_YN": "N",
      "SCHUL_NM": "영훈초등학교"
    },
    {
      "SCHUL_CRSE_SC_VALUE_NM": "초",
      "FOND_SC_CODE": "사립",
      "SCHUL_KND_SC_CODE": "02",
      "ADRCD_NM": "서울특별시 성북구",
      "SCHUL_CRSE_SC_VALUE": "2",
      "JU_ORG_NM": "서울특별시성북강북교육지원청",
      "ATPT_OFCDC_ORG_NM": "서울특별시교육청",
      "JU_ORG_CODE": "B100000348",
      "AMT8": 0,
      "PBAN_EXCP_YN": "N",
      "AMT7": 274939640,
      "FAS_DTN_SC_CODE": "미지정",
      "PBAN_REV_EX_SC_CODE": "결산세출",
      "AMT6": 589797057,
      "AMT5": 710260173,
      "AMT4": 2169552624,
      "AMT3": 575823170,
      "AMT2": 1631299638,
      "SCHUL_CODE": "S010002328",
      "AMT1": 3512794244,
      "YESAN_PER_HEAD": 16751268.2,
      "ATPT_OFCDC_ORG_CODE": "B100000001",
      "LCTN_SC_CODE": "01",
      "BNHH_YN": "N",
      "SCHUL_NM": "우촌초등학교"
    },
    {
      "SCHUL_CRSE_SC_VALUE_NM": "초",
      "FOND_SC_CODE": "사립",
      "SCHUL_KND_SC_CODE": "02",
      "ADRCD_NM": "서울특별시 서초구",
      "SCHUL_CRSE_SC_VALUE": "2",
      "JU_ORG_NM": "서울특별시강남서초교육지원청",
      "ATPT_OFCDC_ORG_NM": "서울특별시교육청",
      "JU_ORG_CODE": "B100000249",
      "AMT8": 0,
      "PBAN_EXCP_YN": "N",
      "AMT7": 369503924,
      "FAS_DTN_SC_CODE": "복식부기",
      "PBAN_REV_EX_SC_CODE": "결산세출",
      "AMT6": 749401314,
      "AMT5": 373914140,
      "AMT4": 613951990,
      "AMT3": 750328230,
      "AMT2": 1516439430,
      "SCHUL_CODE": "S010002365",
      "AMT1": 4434355090,
      "YESAN_PER_HEAD": 12914800.8,
      "ATPT_OFCDC_ORG_CODE": "B100000001",
      "LCTN_SC_CODE": "01",
      "BNHH_YN": "N",
      "SCHUL_NM": "계성초등학교"
    },
    {
      "FOND_SC_CODE": "사립",
      "SCHUL_KND_SC_CODE": "02",
      "ADRCD_NM": "서울특별시 중구",
      "JU_ORG_NM": "서울특별시중부교육지원청",
      "ATPT_OFCDC_ORG_NM": "서울특별시교육청",
      "JU_ORG_CODE": "B100000359",
      "AMT8": 0,
      "PBAN_EXCP_YN": "N",
      "AMT7": 2720667890,
      "FAS_DTN_SC_CODE": "미지정",
      "PBAN_REV_EX_SC_CODE": "결산세출",
      "AMT6": 360117653,
      "AMT5": 315238630,
      "AMT4": 605252640,
      "AMT3": 1188902654,
      "AMT2": 1551695180,
      "SCHUL_CODE": "S010002366",
      "AMT1": 2592691840,
      "YESAN_PER_HEAD": 17033880.5,
      "ATPT_OFCDC_ORG_CODE": "B100000001",
      "LCTN_SC_CODE": "01",
      "BNHH_YN": "N",
      "SCHUL_NM": "동산초등학교"
    },
    {
      "FOND_SC_CODE": "사립",
      "SCHUL_KND_SC_CODE": "02",
      "ADRCD_NM": "서울특별시 중구",
      "JU_ORG_NM": "서울특별시중부교육지원청",
      "ATPT_OFCDC_ORG_NM": "서울특별시교육청",
      "JU_ORG_CODE": "B100000359",
      "AMT8": 0,
      "PBAN_EXCP_YN": "N",
      "AMT7": 323991270,
      "FAS_DTN_SC_CODE": "복식부기",
      "PBAN_REV_EX_SC_CODE": "결산세출",
      "AMT6": 530271311,
      "AMT5": 252483164,
      "AMT4": 574686050,
      "AMT3": 288712833,
      "AMT2": 1965167796,
      "SCHUL_CODE": "S010002367",
      "AMT1": 3442839850,
      "YESAN_PER_HEAD": 14756304.5,
      "ATPT_OFCDC_ORG_CODE": "B100000001",
      "LCTN_SC_CODE": "01",
      "BNHH_YN": "N",
      "SCHUL_NM": "리라초등학교"
    },
    {
      "SCHUL_CRSE_SC_VALUE_NM": "초",
      "FOND_SC_CODE": "사립",
      "SCHUL_KND_SC_CODE": "02",
      "ADRCD_NM": "서울특별시 종로구",
      "SCHUL_CRSE_SC_VALUE": "2",
      "JU_ORG_NM": "서울특별시중부교육지원청",
      "ATPT_OFCDC_ORG_NM": "서울특별시교육청",
      "JU_ORG_CODE": "B100000359",
      "AMT8": 40610560,
      "PBAN_EXCP_YN": "N",
      "AMT7": 168020480,
      "FAS_DTN_SC_CODE": "미지정",
      "PBAN_REV_EX_SC_CODE": "결산세출",
      "AMT6": 141311176,
      "AMT5": 385003188,
      "AMT4": 596076420,
      "AMT3": 491372184,
      "AMT2": 943401266,
      "SCHUL_CODE": "S010002368",
      "AMT1": 1554385740,
      "YESAN_PER_HEAD": 12450089.4,
      "ATPT_OFCDC_ORG_CODE": "B100000001",
      "LCTN_SC_CODE": "01",
      "BNHH_YN": "N",
      "SCHUL_NM": "상명대학교사범대학부속초등학교"
    },
    {
      "FOND_SC_CODE": "사립",
      "SCHUL_KND_SC_CODE": "02",
      "ADRCD_NM": "서울특별시 중구",
      "JU_ORG_NM": "서울특별시중부교육지원청",
      "ATPT_OFCDC_ORG_NM": "서울특별시교육청",
      "JU_ORG_CODE": "B100000359",
      "AMT8": 3492000,
      "PBAN_EXCP_YN": "N",
      "AMT7": 95018000,
      "FAS_DTN_SC_CODE": "미지정",
      "PBAN_REV_EX_SC_CODE": "결산세출",
      "AMT6": 408116316,
      "AMT5": 297070150,
      "AMT4": 199255380,
      "AMT3": 1226294147,
      "AMT2": 1639722782,
      "SCHUL_CODE": "S010002403",
      "AMT1": 2604935180,
      "YESAN_PER_HEAD": 12921964,
      "ATPT_OFCDC_ORG_CODE": "B100000001",
      "LCTN_SC_CODE": "01",
      "BNHH_YN": "N",
      "SCHUL_NM": "숭의초등학교"
    },
    {
      "FOND_SC_CODE": "사립",
      "SCHUL_KND_SC_CODE": "02",
      "ADRCD_NM": "서울특별시 용산구",
      "JU_ORG_NM": "서울특별시중부교육지원청",
      "ATPT_OFCDC_ORG_NM": "서울특별시교육청",
      "JU_ORG_CODE": "B100000359",
      "AMT8": 0,
      "PBAN_EXCP_YN": "N",
      "AMT7": 0,
      "FAS_DTN_SC_CODE": "복식부기",
      "PBAN_REV_EX_SC_CODE": "결산세출",
      "AMT6": 326924565,
      "AMT5": 488179415,
      "AMT4": 459839570,
      "AMT3": 249402494,
      "AMT2": 772001495,
      "SCHUL_CODE": "S010002404",
      "AMT1": 1872365300,
      "YESAN_PER_HEAD": 11547681,
      "ATPT_OFCDC_ORG_CODE": "B100000001",
      "LCTN_SC_CODE": "01",
      "BNHH_YN": "N",
      "SCHUL_NM": "신광초등학교"
    },
    {
      "FOND_SC_CODE": "사립",
      "SCHUL_KND_SC_CODE": "02",
      "ADRCD_NM": "서울특별시 종로구",
      "JU_ORG_NM": "서울특별시중부교육지원청",
      "ATPT_OFCDC_ORG_NM": "서울특별시교육청",
      "JU_ORG_CODE": "B100000359",
      "AMT8": 0,
      "PBAN_EXCP_YN": "N",
      "AMT7": 143676490,
      "FAS_DTN_SC_CODE": "복식부기",
      "PBAN_REV_EX_SC_CODE": "결산세출",
      "AMT6": 285019799,
      "AMT5": 76436520,
      "AMT4": 215109050,
      "AMT3": 240822930,
      "AMT2": 358299010,
      "SCHUL_CODE": "S010002405",
      "AMT1": 1029286970,
      "YESAN_PER_HEAD": 13980064.1,
      "ATPT_OFCDC_ORG_CODE": "B100000001",
      "LCTN_SC_CODE": "01",
      "BNHH_YN": "N",
      "SCHUL_NM": "운현초등학교"
    },
    {
      "SCHUL_CRSE_SC_VALUE_NM": "초",
      "FOND_SC_CODE": "사립",
      "SCHUL_KND_SC_CODE": "02",
      "ADRCD_NM": "부산광역시 중구",
      "SCHUL_CRSE_SC_VALUE": "2",
      "JU_ORG_NM": "부산광역시서부교육지원청",
      "ATPT_OFCDC_ORG_NM": "부산광역시교육청",
      "JU_ORG_CODE": "C100000284",
      "AMT8": 0,
      "PBAN_EXCP_YN": "N",
      "AMT7": 175959940,
      "FAS_DTN_SC_CODE": "복식부기",
      "PBAN_REV_EX_SC_CODE": "결산세출",
      "AMT6": 614091247,
      "AMT5": 160038960,
      "AMT4": 1837751643,
      "AMT3": 1529326783,
      "AMT2": 1957757810,
      "SCHUL_CODE": "S020000626",
      "AMT1": 2492952927,
      "YESAN_PER_HEAD": 18152959.2,
      "ATPT_OFCDC_ORG_CODE": "C100000001",
      "LCTN_SC_CODE": "02",
      "BNHH_YN": "N",
      "SCHUL_NM": "남성초등학교"
    },
    {
      "FOND_SC_CODE": "사립",
      "SCHUL_KND_SC_CODE": "02",
      "ADRCD_NM": "부산광역시 금정구",
      "JU_ORG_NM": "부산광역시동래교육지원청",
      "ATPT_OFCDC_ORG_NM": "부산광역시교육청",
      "JU_ORG_CODE": "C100000202",
      "AMT8": 0,
      "PBAN_EXCP_YN": "N",
      "AMT7": 135900530,
      "FAS_DTN_SC_CODE": "복식부기",
      "PBAN_REV_EX_SC_CODE": "결산세출",
      "AMT6": 230145092,
      "AMT5": 206422360,
      "AMT4": 600819200,
      "AMT3": 647048790,
      "AMT2": 1012960405,
      "SCHUL_CODE": "S020000642",
      "AMT1": 1056156390,
      "YESAN_PER_HEAD": 12836477.8,
      "ATPT_OFCDC_ORG_CODE": "C100000001",
      "LCTN_SC_CODE": "02",
      "BNHH_YN": "N",
      "SCHUL_NM": "부산삼육초등학교"
    },
    {
      "FOND_SC_CODE": "사립",
      "SCHUL_KND_SC_CODE": "02",
      "ADRCD_NM": "부산광역시 금정구",
      "JU_ORG_NM": "부산광역시동래교육지원청",
      "ATPT_OFCDC_ORG_NM": "부산광역시교육청",
      "JU_ORG_CODE": "C100000202",
      "AMT8": 0,
      "PBAN_EXCP_YN": "N",
      "AMT7": 4895061940,
      "FAS_DTN_SC_CODE": "복식부기",
      "PBAN_REV_EX_SC_CODE": "결산세출",
      "AMT6": 665058650,
      "AMT5": 394296550,
      "AMT4": 229628150,
      "AMT3": 1164755040,
      "AMT2": 1639419470,
      "SCHUL_CODE": "S020000813",
      "AMT1": 3120528720,
      "YESAN_PER_HEAD": 19561790.8,
      "ATPT_OFCDC_ORG_CODE": "C100000001",
      "LCTN_SC_CODE": "02",
      "BNHH_YN": "N",
      "SCHUL_NM": "동래초등학교"
    },
    {
      "FOND_SC_CODE": "사립",
      "SCHUL_KND_SC_CODE": "02",
      "ADRCD_NM": "부산광역시 동래구",
      "JU_ORG_NM": "부산광역시동래교육지원청",
      "ATPT_OFCDC_ORG_NM": "부산광역시교육청",
      "JU_ORG_CODE": "C100000202",
      "AMT8": 0,
      "PBAN_EXCP_YN": "N",
      "AMT7": 822521800,
      "FAS_DTN_SC_CODE": "복식부기",
      "PBAN_REV_EX_SC_CODE": "결산세출",
      "AMT6": 149986620,
      "AMT5": 73838930,
      "AMT4": 500729120,
      "AMT3": 542661870,
      "AMT2": 1003000326,
      "SCHUL_CODE": "S020000836",
      "AMT1": 2034909180,
      "YESAN_PER_HEAD": 15680880.3,
      "ATPT_OFCDC_ORG_CODE": "C100000001",
      "LCTN_SC_CODE": "02",
      "BNHH_YN": "N",
      "SCHUL_NM": "혜화초등학교"
    },
    {
      "FOND_SC_CODE": "사립",
      "SCHUL_KND_SC_CODE": "02",
      "ADRCD_NM": "부산광역시 부산진구",
      "JU_ORG_NM": "부산광역시남부교육지원청",
      "ATPT_OFCDC_ORG_NM": "부산광역시교육청",
      "JU_ORG_CODE": "C100000175",
      "AMT8": 0,
      "PBAN_EXCP_YN": "N",
      "AMT7": 776047300,
      "FAS_DTN_SC_CODE": "미지정",
      "PBAN_REV_EX_SC_CODE": "결산세출",
      "AMT6": 439320500,
      "AMT5": 813629890,
      "AMT4": 1350225290,
      "AMT3": 855015889,
      "AMT2": 1743810070,
      "SCHUL_CODE": "S020001006",
      "AMT1": 3155901326,
      "YESAN_PER_HEAD": 12276814.9,
      "ATPT_OFCDC_ORG_CODE": "C100000001",
      "LCTN_SC_CODE": "02",
      "BNHH_YN": "N",
      "SCHUL_NM": "동성초등학교"
    },
    {
      "FOND_SC_CODE": "사립",
      "SCHUL_KND_SC_CODE": "02",
      "ADRCD_NM": "부산광역시 서구",
      "JU_ORG_NM": "부산광역시서부교육지원청",
      "ATPT_OFCDC_ORG_NM": "부산광역시교육청",
      "JU_ORG_CODE": "C100000284",
      "AMT8": 19920060,
      "PBAN_EXCP_YN": "N",
      "AMT7": 125901180,
      "FAS_DTN_SC_CODE": "미지정",
      "PBAN_REV_EX_SC_CODE": "결산세출",
      "AMT6": 201810170,
      "AMT5": 158141670,
      "AMT4": 148493920,
      "AMT3": 126164620,
      "AMT2": 163027180,
      "SCHUL_CODE": "S020002091",
      "AMT1": 1099470310,
      "YESAN_PER_HEAD": 34048818.5,
      "ATPT_OFCDC_ORG_CODE": "C100000001",
      "LCTN_SC_CODE": "02",
      "BNHH_YN": "N",
      "SCHUL_NM": "부산알로이시오초등학교"
    },
    {
      "FOND_SC_CODE": "사립",
      "SCHUL_KND_SC_CODE": "02",
      "ADRCD_NM": "대구광역시 달서구",
      "JU_ORG_NM": "대구광역시남부교육지원청",
      "ATPT_OFCDC_ORG_NM": "대구광역시교육청",
      "JU_ORG_CODE": "D100000117",
      "AMT8": 0,
      "PBAN_EXCP_YN": "N",
      "AMT7": 353304520,
      "FAS_DTN_SC_CODE": "복식부기",
      "PBAN_REV_EX_SC_CODE": "결산세출",
      "AMT6": 319661698,
      "AMT5": 397515724,
      "AMT4": 364933690,
      "AMT3": 898544192,
      "AMT2": 1424601530,
      "SCHUL_CODE": "S030000459",
      "AMT1": 2613411230,
      "YESAN_PER_HEAD": 12160253,
      "ATPT_OFCDC_ORG_CODE": "D100000001",
      "LCTN_SC_CODE": "03",
      "BNHH_YN": "N",
      "SCHUL_NM": "효성초등학교"
    },
    {
      "SCHUL_CRSE_SC_VALUE_NM": "초",
      "FOND_SC_CODE": "사립",
      "SCHUL_KND_SC_CODE": "02",
      "ADRCD_NM": "대구광역시 중구",
      "SCHUL_CRSE_SC_VALUE": "2",
      "JU_ORG_NM": "대구광역시동부교육지원청",
      "ATPT_OFCDC_ORG_NM": "대구광역시교육청",
      "JU_ORG_CODE": "D100000171",
      "AMT8": 0,
      "PBAN_EXCP_YN": "N",
      "AMT7": 480858850,
      "FAS_DTN_SC_CODE": "복식부기",
      "PBAN_REV_EX_SC_CODE": "결산세출",
      "AMT6": 639937330,
      "AMT5": 671694407,
      "AMT4": 494945110,
      "AMT3": 1248511631,
      "AMT2": 1739508779,
      "SCHUL_CODE": "S030000658",
      "AMT1": 3248980300,
      "YESAN_PER_HEAD": 11693328.4,
      "ATPT_OFCDC_ORG_CODE": "D100000001",
      "LCTN_SC_CODE": "03",
      "BNHH_YN": "N",
      "SCHUL_NM": "계성초등학교"
    },
    {
      "FOND_SC_CODE": "사립",
      "SCHUL_KND_SC_CODE": "02",
      "ADRCD_NM": "대구광역시 수성구",
      "JU_ORG_NM": "대구광역시동부교육지원청",
      "ATPT_OFCDC_ORG_NM": "대구광역시교육청",
      "JU_ORG_CODE": "D100000171",
      "AMT8": 0,
      "PBAN_EXCP_YN": "N",
      "AMT7": 55193970,
      "FAS_DTN_SC_CODE": "미지정",
      "PBAN_REV_EX_SC_CODE": "결산세출",
      "AMT6": 133797804,
      "AMT5": 198234516,
      "AMT4": 546297610,
      "AMT3": 396755350,
      "AMT2": 414297136,
      "SCHUL_CODE": "S030000722",
      "AMT1": 713607265,
      "YESAN_PER_HEAD": 11123002.9,
      "ATPT_OFCDC_ORG_CODE": "D100000001",
      "LCTN_SC_CODE": "03",
      "BNHH_YN": "N",
      "SCHUL_NM": "대구삼육초등학교"
    },
    {
      "FOND_SC_CODE": "사립",
      "SCHUL_KND_SC_CODE": "02",
      "ADRCD_NM": "대구광역시 동구",
      "JU_ORG_NM": "대구광역시동부교육지원청",
      "ATPT_OFCDC_ORG_NM": "대구광역시교육청",
      "JU_ORG_CODE": "D100000171",
      "AMT8": 0,
      "PBAN_EXCP_YN": "N",
      "AMT7": 534362350,
      "FAS_DTN_SC_CODE": "복식부기",
      "PBAN_REV_EX_SC_CODE": "결산세출",
      "AMT6": 685988406,
      "AMT5": 390821932,
      "AMT4": 820556040,
      "AMT3": 1581121050,
      "AMT2": 1846670820,
      "SCHUL_CODE": "S030000723",
      "AMT1": 3152846230,
      "YESAN_PER_HEAD": 12345708,
      "ATPT_OFCDC_ORG_CODE": "D100000001",
      "LCTN_SC_CODE": "03",
      "BNHH_YN": "N",
      "SCHUL_NM": "영신초등학교"
    },
    {
      "FOND_SC_CODE": "사립",
      "SCHUL_KND_SC_CODE": "02",
      "ADRCD_NM": "인천광역시 동구",
      "JU_ORG_NM": "인천광역시남부교육지원청",
      "ATPT_OFCDC_ORG_NM": "인천광역시교육청",
      "JU_ORG_CODE": "E100000082",
      "AMT8": 5361480,
      "PBAN_EXCP_YN": "N",
      "AMT7": 1601076080,
      "FAS_DTN_SC_CODE": "복식부기",
      "PBAN_REV_EX_SC_CODE": "결산세출",
      "AMT6": 248355474,
      "AMT5": 305009020,
      "AMT4": 663880400,
      "AMT3": 691793270,
      "AMT2": 791001680,
      "SCHUL_CODE": "S040000464",
      "AMT1": 1323957907,
      "YESAN_PER_HEAD": 17874397.8,
      "ATPT_OFCDC_ORG_CODE": "E100000001",
      "LCTN_SC_CODE": "04",
      "BNHH_YN": "N",
      "SCHUL_NM": "영화초등학교"
    },
    {
      "SCHUL_CRSE_SC_VALUE_NM": "초",
      "FOND_SC_CODE": "사립",
      "SCHUL_KND_SC_CODE": "02",
      "ADRCD_NM": "인천광역시 중구",
      "SCHUL_CRSE_SC_VALUE": "2",
      "JU_ORG_NM": "인천광역시남부교육지원청",
      "ATPT_OFCDC_ORG_NM": "인천광역시교육청",
      "JU_ORG_CODE": "E100000082",
      "AMT8": 0,
      "PBAN_EXCP_YN": "N",
      "AMT7": 0,
      "FAS_DTN_SC_CODE": "복식부기",
      "PBAN_REV_EX_SC_CODE": "결산세출",
      "AMT6": 348518830,
      "AMT5": 774060010,
      "AMT4": 754305060,
      "AMT3": 1224245530,
      "AMT2": 1281326520,
      "SCHUL_CODE": "S040000470",
      "AMT1": 1983523220,
      "YESAN_PER_HEAD": 12886597.5,
      "ATPT_OFCDC_ORG_CODE": "E100000001",
      "LCTN_SC_CODE": "04",
      "BNHH_YN": "N",
      "SCHUL_NM": "인성초등학교"
    },
    {
      "FOND_SC_CODE": "사립",
      "SCHUL_KND_SC_CODE": "02",
      "ADRCD_NM": "인천광역시 동구",
      "JU_ORG_NM": "인천광역시남부교육지원청",
      "ATPT_OFCDC_ORG_NM": "인천광역시교육청",
      "JU_ORG_CODE": "E100000082",
      "AMT8": 4611720,
      "PBAN_EXCP_YN": "N",
      "AMT7": 647660580,
      "FAS_DTN_SC_CODE": "복식부기",
      "PBAN_REV_EX_SC_CODE": "결산세출",
      "AMT6": 218412930,
      "AMT5": 549848190,
      "AMT4": 603832460,
      "AMT3": 530008700,
      "AMT2": 1096212400,
      "SCHUL_CODE": "S040000478",
      "AMT1": 1436084820,
      "YESAN_PER_HEAD": 13212134.5,
      "ATPT_OFCDC_ORG_CODE": "E100000001",
      "LCTN_SC_CODE": "04",
      "BNHH_YN": "N",
      "SCHUL_NM": "인천동명초등학교"
    },
    {
      "FOND_SC_CODE": "사립",
      "SCHUL_KND_SC_CODE": "02",
      "ADRCD_NM": "인천광역시 연수구",
      "JU_ORG_NM": "인천광역시동부교육지원청",
      "ATPT_OFCDC_ORG_NM": "인천광역시교육청",
      "JU_ORG_CODE": "E100000117",
      "AMT8": 20886070,
      "PBAN_EXCP_YN": "N",
      "AMT7": 1528327770,
      "FAS_DTN_SC_CODE": "미지정",
      "PBAN_REV_EX_SC_CODE": "결산세출",
      "AMT6": 472558901,
      "AMT5": 392616331,
      "AMT4": 440304170,
      "AMT3": 717400213,
      "AMT2": 1385662630,
      "SCHUL_CODE": "S040000658",
      "AMT1": 2312511675,
      "YESAN_PER_HEAD": 14990242.8,
      "ATPT_OFCDC_ORG_CODE": "E100000001",
      "LCTN_SC_CODE": "04",
      "BNHH_YN": "N",
      "SCHUL_NM": "인천박문초등학교"
    },
    {
      "SCHUL_CRSE_SC_VALUE_NM": "초",
      "FOND_SC_CODE": "사립",
      "SCHUL_KND_SC_CODE": "02",
      "ADRCD_NM": "인천광역시 부평구",
      "SCHUL_CRSE_SC_VALUE": "2",
      "JU_ORG_NM": "인천광역시북부교육지원청",
      "ATPT_OFCDC_ORG_NM": "인천광역시교육청",
      "JU_ORG_CODE": "E100000150",
      "AMT8": 2306120,
      "PBAN_EXCP_YN": "N",
      "AMT7": 0,
      "FAS_DTN_SC_CODE": "복식부기",
      "PBAN_REV_EX_SC_CODE": "결산세출",
      "AMT6": 189254810,
      "AMT5": 206648640,
      "AMT4": 464701720,
      "AMT3": 457724610,
      "AMT2": 720232110,
      "SCHUL_CODE": "S040000888",
      "AMT1": 1370666620,
      "YESAN_PER_HEAD": 11040565.1,
      "ATPT_OFCDC_ORG_CODE": "E100000001",
      "LCTN_SC_CODE": "04",
      "BNHH_YN": "N",
      "SCHUL_NM": "한일초등학교"
    },
    {
      "FOND_SC_CODE": "사립",
      "SCHUL_KND_SC_CODE": "02",
      "ADRCD_NM": "광주광역시 서구",
      "JU_ORG_NM": "광주광역시서부교육지원청",
      "ATPT_OFCDC_ORG_NM": "광주광역시교육청",
      "JU_ORG_CODE": "F100000072",
      "AMT8": 0,
      "PBAN_EXCP_YN": "N",
      "AMT7": 127453030,
      "FAS_DTN_SC_CODE": "미지정",
      "PBAN_REV_EX_SC_CODE": "결산세출",
      "AMT6": 380239600,
      "AMT5": 143451830,
      "AMT4": 575269320,
      "AMT3": 737608610,
      "AMT2": 1294402200,
      "SCHUL_CODE": "S050000252",
      "AMT1": 2065043320,
      "YESAN_PER_HEAD": 10541520.6,
      "ATPT_OFCDC_ORG_CODE": "F100000001",
      "LCTN_SC_CODE": "05",
      "BNHH_YN": "N",
      "SCHUL_NM": "살레시오초등학교"
    },
    {
      "SCHUL_CRSE_SC_VALUE_NM": "초",
      "FOND_SC_CODE": "사립",
      "SCHUL_KND_SC_CODE": "02",
      "ADRCD_NM": "광주광역시 남구",
      "SCHUL_CRSE_SC_VALUE": "2",
      "JU_ORG_NM": "광주광역시서부교육지원청",
      "ATPT_OFCDC_ORG_NM": "광주광역시교육청",
      "JU_ORG_CODE": "F100000072",
      "AMT8": 377000,
      "PBAN_EXCP_YN": "N",
      "AMT7": 229467980,
      "FAS_DTN_SC_CODE": "복식부기",
      "PBAN_REV_EX_SC_CODE": "결산세출",
      "AMT6": 400588194,
      "AMT5": 225027020,
      "AMT4": 1282544965,
      "AMT3": 759688600,
      "AMT2": 1115059780,
      "SCHUL_CODE": "S050000418",
      "AMT1": 1971001010,
      "YESAN_PER_HEAD": 10497815,
      "ATPT_OFCDC_ORG_CODE": "F100000001",
      "LCTN_SC_CODE": "05",
      "BNHH_YN": "N",
      "SCHUL_NM": "광주삼육초등학교"
    },
    {
      "FOND_SC_CODE": "사립",
      "SCHUL_KND_SC_CODE": "02",
      "ADRCD_NM": "광주광역시 남구",
      "JU_ORG_NM": "광주광역시서부교육지원청",
      "ATPT_OFCDC_ORG_NM": "광주광역시교육청",
      "JU_ORG_CODE": "F100000072",
      "AMT8": 845230,
      "PBAN_EXCP_YN": "N",
      "AMT7": 825282860,
      "FAS_DTN_SC_CODE": "복식부기",
      "PBAN_REV_EX_SC_CODE": "결산세출",
      "AMT6": 319307979,
      "AMT5": 162022467,
      "AMT4": 716502280,
      "AMT3": 613811800,
      "AMT2": 961978070,
      "SCHUL_CODE": "S050000421",
      "AMT1": 2220001120,
      "YESAN_PER_HEAD": 10318708.9,
      "ATPT_OFCDC_ORG_CODE": "F100000001",
      "LCTN_SC_CODE": "05",
      "BNHH_YN": "N",
      "SCHUL_NM": "광주송원초등학교"
    },
    {
      "FOND_SC_CODE": "사립",
      "SCHUL_KND_SC_CODE": "02",
      "ADRCD_NM": "대전광역시 중구",
      "JU_ORG_NM": "대전광역시동부교육지원청",
      "ATPT_OFCDC_ORG_NM": "대전광역시교육청",
      "JU_ORG_CODE": "G100000108",
      "AMT8": 1869910,
      "PBAN_EXCP_YN": "N",
      "AMT7": 365341190,
      "FAS_DTN_SC_CODE": "복식부기",
      "PBAN_REV_EX_SC_CODE": "결산세출",
      "AMT6": 691977396,
      "AMT5": 226070940,
      "AMT4": 1116612830,
      "AMT3": 1031932654,
      "AMT2": 1495162540,
      "SCHUL_CODE": "S060000341",
      "AMT1": 3203584000,
      "YESAN_PER_HEAD": 12746945.9,
      "ATPT_OFCDC_ORG_CODE": "G100000001",
      "LCTN_SC_CODE": "06",
      "BNHH_YN": "N",
      "SCHUL_NM": "대전성모초등학교"
    },
    {
      "SCHUL_CRSE_SC_VALUE_NM": "초",
      "FOND_SC_CODE": "사립",
      "SCHUL_KND_SC_CODE": "02",
      "ADRCD_NM": "대전광역시 서구",
      "SCHUL_CRSE_SC_VALUE": "2",
      "JU_ORG_NM": "대전광역시서부교육지원청",
      "ATPT_OFCDC_ORG_NM": "대전광역시교육청",
      "JU_ORG_CODE": "G100000138",
      "AMT8": 9765620,
      "PBAN_EXCP_YN": "N",
      "AMT7": 0,
      "FAS_DTN_SC_CODE": "미지정",
      "PBAN_REV_EX_SC_CODE": "결산세출",
      "AMT6": 328002680,
      "AMT5": 449814920,
      "AMT4": 757996290,
      "AMT3": 750010440,
      "AMT2": 1218954650,
      "SCHUL_CODE": "S060000520",
      "AMT1": 1853857910,
      "YESAN_PER_HEAD": 9385319.1,
      "ATPT_OFCDC_ORG_CODE": "G100000001",
      "LCTN_SC_CODE": "06",
      "BNHH_YN": "N",
      "SCHUL_NM": "대전삼육초등학교"
    },
    {
      "FOND_SC_CODE": "사립",
      "SCHUL_KND_SC_CODE": "02",
      "ADRCD_NM": "경기도 남양주시",
      "JU_ORG_NM": "경기도구리남양주교육지원청",
      "ATPT_OFCDC_ORG_NM": "경기도교육청",
      "JU_ORG_CODE": "J100000170",
      "AMT8": 7642820,
      "PBAN_EXCP_YN": "N",
      "AMT7": 186925190,
      "FAS_DTN_SC_CODE": "미지정",
      "PBAN_REV_EX_SC_CODE": "결산세출",
      "AMT6": 470576908,
      "AMT5": 84102790,
      "AMT4": 729925300,
      "AMT3": 2097832270,
      "AMT2": 1388959280,
      "SCHUL_CODE": "S090001641",
      "AMT1": 2006002770,
      "YESAN_PER_HEAD": 13305281.2,
      "ATPT_OFCDC_ORG_CODE": "J100000001",
      "LCTN_SC_CODE": "10",
      "BNHH_YN": "N",
      "SCHUL_NM": "심석초등학교"
    },
    {
      "FOND_SC_CODE": "사립",
      "SCHUL_KND_SC_CODE": "02",
      "ADRCD_NM": "경기도 수원시 영통구",
      "JU_ORG_NM": "경기도수원교육지원청",
      "ATPT_OFCDC_ORG_NM": "경기도교육청",
      "JU_ORG_CODE": "J100000250",
      "AMT8": 38796200,
      "PBAN_EXCP_YN": "N",
      "AMT7": 1421189830,
      "FAS_DTN_SC_CODE": "복식부기",
      "PBAN_REV_EX_SC_CODE": "결산세출",
      "AMT6": 235777790,
      "AMT5": 272362660,
      "AMT4": 498653831,
      "AMT3": 231190868,
      "AMT2": 1170344630,
      "SCHUL_CODE": "S090002469",
      "AMT1": 3043627320,
      "YESAN_PER_HEAD": 13714172.9,
      "ATPT_OFCDC_ORG_CODE": "J100000001",
      "LCTN_SC_CODE": "10",
      "BNHH_YN": "N",
      "SCHUL_NM": "소화초등학교"
    },
    {
      "SCHUL_CRSE_SC_VALUE_NM": "초",
      "FOND_SC_CODE": "사립",
      "SCHUL_KND_SC_CODE": "02",
      "ADRCD_NM": "경기도 수원시 영통구",
      "SCHUL_CRSE_SC_VALUE": "2",
      "JU_ORG_NM": "경기도수원교육지원청",
      "ATPT_OFCDC_ORG_NM": "경기도교육청",
      "JU_ORG_CODE": "J100000250",
      "AMT8": 0,
      "PBAN_EXCP_YN": "N",
      "AMT7": 991315839,
      "FAS_DTN_SC_CODE": "미지정",
      "PBAN_REV_EX_SC_CODE": "결산세출",
      "AMT6": 1334334323,
      "AMT5": 147853949,
      "AMT4": 461532767,
      "AMT3": 857003483,
      "AMT2": 1501848230,
      "SCHUL_CODE": "S090002504",
      "AMT1": 6233988654,
      "YESAN_PER_HEAD": 13530372.4,
      "ATPT_OFCDC_ORG_CODE": "J100000001",
      "LCTN_SC_CODE": "10",
      "BNHH_YN": "N",
      "SCHUL_NM": "중앙기독초등학교"
    },
    {
      "SCHUL_CRSE_SC_VALUE_NM": "초",
      "FOND_SC_CODE": "사립",
      "SCHUL_KND_SC_CODE": "02",
      "ADRCD_NM": "강원특별자치도 동해시",
      "SCHUL_CRSE_SC_VALUE": "2",
      "JU_ORG_NM": "강원특별자치도동해교육지원청",
      "ATPT_OFCDC_ORG_NM": "강원특별자치도교육청",
      "JU_ORG_CODE": "K100000121",
      "AMT8": 14005630,
      "PBAN_EXCP_YN": "N",
      "AMT7": 554777510,
      "FAS_DTN_SC_CODE": "미지정",
      "PBAN_REV_EX_SC_CODE": "결산세출",
      "AMT6": 107983160,
      "AMT5": 209077295,
      "AMT4": 377922410,
      "AMT3": 382034170,
      "AMT2": 425539940,
      "SCHUL_CODE": "S100000778",
      "AMT1": 912331920,
      "YESAN_PER_HEAD": 13624073.2,
      "ATPT_OFCDC_ORG_CODE": "K100000001",
      "LCTN_SC_CODE": "11",
      "BNHH_YN": "N",
      "SCHUL_NM": "동해삼육초등학교"
    },
    {
      "FOND_SC_CODE": "사립",
      "SCHUL_KND_SC_CODE": "02",
      "ADRCD_NM": "강원특별자치도 원주시",
      "JU_ORG_NM": "강원특별자치도원주교육지원청",
      "ATPT_OFCDC_ORG_NM": "강원특별자치도교육청",
      "JU_ORG_CODE": "K100000198",
      "AMT8": 0,
      "PBAN_EXCP_YN": "N",
      "AMT7": 966587230,
      "FAS_DTN_SC_CODE": "미지정",
      "PBAN_REV_EX_SC_CODE": "결산세출",
      "AMT6": 221983668,
      "AMT5": 295539060,
      "AMT4": 648425470,
      "AMT3": 657930694,
      "AMT2": 709417185,
      "SCHUL_CODE": "S100001376",
      "AMT1": 2121651120,
      "YESAN_PER_HEAD": 10527218,
      "ATPT_OFCDC_ORG_CODE": "K100000001",
      "LCTN_SC_CODE": "11",
      "BNHH_YN": "N",
      "SCHUL_NM": "원주삼육초등학교"
    },
    {
      "FOND_SC_CODE": "사립",
      "SCHUL_KND_SC_CODE": "02",
      "ADRCD_NM": "강원특별자치도 춘천시",
      "JU_ORG_NM": "강원특별자치도춘천교육지원청",
      "ATPT_OFCDC_ORG_NM": "강원특별자치도교육청",
      "JU_ORG_CODE": "K100000257",
      "AMT8": 39557680,
      "PBAN_EXCP_YN": "N",
      "AMT7": 258750050,
      "FAS_DTN_SC_CODE": "미지정",
      "PBAN_REV_EX_SC_CODE": "결산세출",
      "AMT6": 180784620,
      "AMT5": 114477960,
      "AMT4": 288334230,
      "AMT3": 683974480,
      "AMT2": 863960400,
      "SCHUL_CODE": "S100001896",
      "AMT1": 1238358910,
      "YESAN_PER_HEAD": 12916191.3,
      "ATPT_OFCDC_ORG_CODE": "K100000001",
      "LCTN_SC_CODE": "11",
      "BNHH_YN": "N",
      "SCHUL_NM": "춘천삼육초등학교"
    },
    {
      "SCHUL_CRSE_SC_VALUE_NM": "초",
      "FOND_SC_CODE": "사립",
      "SCHUL_KND_SC_CODE": "02",
      "ADRCD_NM": "충청북도 청주시 청원구",
      "SCHUL_CRSE_SC_VALUE": "2",
      "JU_ORG_NM": "충청북도청주교육지원청",
      "ATPT_OFCDC_ORG_NM": "충청북도교육청",
      "JU_ORG_CODE": "M100000109",
      "AMT8": 0,
      "PBAN_EXCP_YN": "N",
      "AMT7": 848000000,
      "FAS_DTN_SC_CODE": "미지정",
      "PBAN_REV_EX_SC_CODE": "결산세출",
      "AMT6": 264636460,
      "AMT5": 264912030,
      "AMT4": 251549500,
      "AMT3": 1351480310,
      "AMT2": 1324608120,
      "SCHUL_CODE": "S110000935",
      "AMT1": 2321362390,
      "YESAN_PER_HEAD": 12070216.4,
      "ATPT_OFCDC_ORG_CODE": "M100000001",
      "LCTN_SC_CODE": "12",
      "BNHH_YN": "N",
      "SCHUL_NM": "청주대성초등학교"
    },
    {
      "FOND_SC_CODE": "사립",
      "SCHUL_KND_SC_CODE": "02",
      "ADRCD_NM": "충청남도 홍성군",
      "JU_ORG_NM": "충청남도홍성교육지원청",
      "ATPT_OFCDC_ORG_NM": "충청남도교육청",
      "JU_ORG_CODE": "N100000113",
      "AMT8": 0,
      "PBAN_EXCP_YN": "N",
      "AMT7": 572643310,
      "FAS_DTN_SC_CODE": "미지정",
      "PBAN_REV_EX_SC_CODE": "결산세출",
      "AMT6": 146046030,
      "AMT5": 72904280,
      "AMT4": 295765020,
      "AMT3": 681698730,
      "AMT2": 523089410,
      "SCHUL_CODE": "S120001231",
      "AMT1": 913222080,
      "YESAN_PER_HEAD": 17907088.6,
      "ATPT_OFCDC_ORG_CODE": "N100000001",
      "LCTN_SC_CODE": "13",
      "BNHH_YN": "N",
      "SCHUL_NM": "서해삼육초등학교"
    },
    {
      "FOND_SC_CODE": "사립",
      "SCHUL_KND_SC_CODE": "02",
      "ADRCD_NM": "전라남도 광양시",
      "JU_ORG_NM": "전라남도광양교육지원청",
      "ATPT_OFCDC_ORG_NM": "전라남도교육청",
      "JU_ORG_CODE": "Q100000065",
      "AMT8": 366689820,
      "PBAN_EXCP_YN": "N",
      "AMT7": 0,
      "FAS_DTN_SC_CODE": "미지정",
      "PBAN_REV_EX_SC_CODE": "결산세출",
      "AMT6": 342417419,
      "AMT5": 1374811050,
      "AMT4": 366870650,
      "AMT3": 194795020,
      "AMT2": 720633620,
      "SCHUL_CODE": "S140000566",
      "AMT1": 2468286340,
      "YESAN_PER_HEAD": 14441841.4,
      "ATPT_OFCDC_ORG_CODE": "Q100000001",
      "LCTN_SC_CODE": "15",
      "BNHH_YN": "N",
      "SCHUL_NM": "광양제철남초등학교"
    },
    {
      "FOND_SC_CODE": "사립",
      "SCHUL_KND_SC_CODE": "02",
      "ADRCD_NM": "전라남도 광양시",
      "JU_ORG_NM": "전라남도광양교육지원청",
      "ATPT_OFCDC_ORG_NM": "전라남도교육청",
      "JU_ORG_CODE": "Q100000065",
      "AMT8": 92803610,
      "PBAN_EXCP_YN": "N",
      "AMT7": 0,
      "FAS_DTN_SC_CODE": "미지정",
      "PBAN_REV_EX_SC_CODE": "결산세출",
      "AMT6": 269934733,
      "AMT5": 628033730,
      "AMT4": 321521459,
      "AMT3": 117357630,
      "AMT2": 460040080,
      "SCHUL_CODE": "S140000567",
      "AMT1": 1932880420,
      "YESAN_PER_HEAD": 15666277.3,
      "ATPT_OFCDC_ORG_CODE": "Q100000001",
      "LCTN_SC_CODE": "15",
      "BNHH_YN": "N",
      "SCHUL_NM": "광양제철초등학교"
    },
    {
      "FOND_SC_CODE": "사립",
      "SCHUL_KND_SC_CODE": "02",
      "ADRCD_NM": "전라남도 여수시",
      "JU_ORG_NM": "전라남도여수교육지원청",
      "ATPT_OFCDC_ORG_NM": "전라남도교육청",
      "JU_ORG_CODE": "Q100000110",
      "AMT8": 64607000,
      "PBAN_EXCP_YN": "N",
      "AMT7": 542419390,
      "FAS_DTN_SC_CODE": "미지정",
      "PBAN_REV_EX_SC_CODE": "결산세출",
      "AMT6": 274822710,
      "AMT5": 677201100,
      "AMT4": 816716450,
      "AMT3": 288530730,
      "AMT2": 932151240,
      "SCHUL_CODE": "S140001425",
      "AMT1": 2930036860,
      "YESAN_PER_HEAD": 10025323.3,
      "ATPT_OFCDC_ORG_CODE": "Q100000001",
      "LCTN_SC_CODE": "15",
      "BNHH_YN": "N",
      "SCHUL_NM": "여도초등학교"
    },
    {
      "SCHUL_CRSE_SC_VALUE_NM": "초",
      "FOND_SC_CODE": "사립",
      "SCHUL_KND_SC_CODE": "02",
      "ADRCD_NM": "경상북도 포항시 남구",
      "SCHUL_CRSE_SC_VALUE": "2",
      "JU_ORG_NM": "경상북도포항교육지원청",
      "ATPT_OFCDC_ORG_NM": "경상북도교육청",
      "JU_ORG_CODE": "R100000619",
      "AMT8": 465730000,
      "PBAN_EXCP_YN": "N",
      "AMT7": 854521220,
      "FAS_DTN_SC_CODE": "복식부기",
      "PBAN_REV_EX_SC_CODE": "결산세출",
      "AMT6": 475430138,
      "AMT5": 473914965,
      "AMT4": 861744930,
      "AMT3": 697487980,
      "AMT2": 1184524824,
      "SCHUL_CODE": "S150003653",
      "AMT1": 3788188890,
      "YESAN_PER_HEAD": 9484421.3,
      "ATPT_OFCDC_ORG_CODE": "R100000001",
      "LCTN_SC_CODE": "16",
      "BNHH_YN": "N",
      "SCHUL_NM": "포항제철초등학교"
    },
    {
      "FOND_SC_CODE": "사립",
      "SCHUL_KND_SC_CODE": "02",
      "ADRCD_NM": "경상북도 포항시 남구",
      "JU_ORG_NM": "경상북도포항교육지원청",
      "ATPT_OFCDC_ORG_NM": "경상북도교육청",
      "JU_ORG_CODE": "R100000619",
      "AMT8": 29764000,
      "PBAN_EXCP_YN": "N",
      "AMT7": 1046533540,
      "FAS_DTN_SC_CODE": "복식부기",
      "PBAN_REV_EX_SC_CODE": "결산세출",
      "AMT6": 466127954,
      "AMT5": 827446489,
      "AMT4": 608765210,
      "AMT3": 840061290,
      "AMT2": 1632409552,
      "SCHUL_CODE": "S150003655",
      "AMT1": 4828848300,
      "YESAN_PER_HEAD": 7564353.4,
      "ATPT_OFCDC_ORG_CODE": "R100000001",
      "LCTN_SC_CODE": "16",
      "BNHH_YN": "N",
      "SCHUL_NM": "포항제철지곡초등학교"
    },
    {
      "SCHUL_CRSE_SC_VALUE_NM": "초",
      "FOND_SC_CODE": "사립",
      "SCHUL_KND_SC_CODE": "02",
      "ADRCD_NM": "경상남도 거제시",
      "SCHUL_CRSE_SC_VALUE": "2",
      "JU_ORG_NM": "거제교육지원청",
      "ATPT_OFCDC_ORG_NM": "경상남도교육청",
      "JU_ORG_CODE": "S100000106",
      "AMT8": 59570850,
      "PBAN_EXCP_YN": "N",
      "AMT7": 1245585980,
      "FAS_DTN_SC_CODE": "복식부기",
      "PBAN_REV_EX_SC_CODE": "결산세출",
      "AMT6": 267796090,
      "AMT5": 175314780,
      "AMT4": 782245650,
      "AMT3": 246828800,
      "AMT2": 980410900,
      "SCHUL_CODE": "S160000787",
      "AMT1": 1894496320,
      "YESAN_PER_HEAD": 11606261.5,
      "ATPT_OFCDC_ORG_CODE": "S100000001",
      "LCTN_SC_CODE": "17",
      "BNHH_YN": "N",
      "SCHUL_NM": "대우초등학교"
    },
    {
      "SCHUL_CRSE_SC_VALUE_NM": "초",
      "FOND_SC_CODE": "사립",
      "SCHUL_KND_SC_CODE": "02",
      "ADRCD_NM": "경상남도 거창군",
      "SCHUL_CRSE_SC_VALUE": "2",
      "JU_ORG_NM": "거창교육지원청",
      "ATPT_OFCDC_ORG_NM": "경상남도교육청",
      "JU_ORG_CODE": "S100000123",
      "AMT8": 39065440,
      "PBAN_EXCP_YN": "N",
      "AMT7": 1015702560,
      "FAS_DTN_SC_CODE": "복식부기",
      "PBAN_REV_EX_SC_CODE": "결산세출",
      "AMT6": 168716950,
      "AMT5": 248213180,
      "AMT4": 277262690,
      "AMT3": 278573760,
      "AMT2": 541253460,
      "SCHUL_CODE": "S160000956",
      "AMT1": 1796872640,
      "YESAN_PER_HEAD": 14455830.1,
      "ATPT_OFCDC_ORG_CODE": "S100000001",
      "LCTN_SC_CODE": "17",
      "BNHH_YN": "N",
      "SCHUL_NM": "샛별초등학교"
    }
  ]
}